image_transform/__init__.py
image_transform/image_transform.py
image_transform-1.1.1.dist-info/LICENSE
image_transform-1.1.1.dist-info/METADATA
image_transform-1.1.1.dist-info/WHEEL
image_transform-1.1.1.dist-info/top_level.txt
image_transform-1.1.1.dist-info/RECORD
