Metadata-Version: 2.1
Name: image-transform
Version: 1.1.1
Summary: Image processing and transformations
Home-page: https://github.com/almishkawi/image_transform
Author: Mo Almishkawi
Author-email: 
License: UNKNOWN
Platform: UNKNOWN
Classifier: Programming Language :: Python :: 3
Classifier: License :: OSI Approved :: MIT License
Classifier: Operating System :: OS Independent
Requires-Python: >=3.6
